isd_tui/__init__.py
isd_tui/architecture.md
isd_tui/derive_terminal_theme.py
isd_tui/dom.tcss
isd_tui/isd.py
isd_tui/keybinding_notes.md
isd_tui-0.6.1.data/data/share/applications/isd.desktop
isd_tui-0.6.1.data/data/share/icons/hicolor/128x128/apps/isd.png
isd_tui-0.6.1.data/data/share/icons/hicolor/256x256/apps/isd.png
isd_tui-0.6.1.data/data/share/icons/hicolor/512x512/apps/isd.png
isd_tui-0.6.1.dist-info/METADATA
isd_tui-0.6.1.dist-info/WHEEL
isd_tui-0.6.1.dist-info/entry_points.txt
isd_tui-0.6.1.dist-info/licenses/LICENSE
isd_tui-0.6.1.dist-info/RECORD
