Metadata-Version: 2.4
Name: isd-tui
Version: 0.6.1
Summary: Interactive systemd TUI
Project-URL: Hompage, https://github.com/kainctl/isd
Project-URL: Documentation, https://kainctl.github.io/isd/
Project-URL: Repository, https://github.com/kainctl/isd
Project-URL: Bug Tracker, https://github.com/kainctl/isd/issues
License-Expression: GPL-3.0-or-later
License-File: LICENSE
Keywords: service-manager,systemd,tui
Classifier: Environment :: Console
Classifier: Intended Audience :: End Users/Desktop
Classifier: Intended Audience :: System Administrators
Classifier: License :: OSI Approved :: GNU General Public License v3 or later (GPLv3+)
Classifier: Operating System :: Unix
Classifier: Programming Language :: Python
Classifier: Topic :: System :: Monitoring
Classifier: Topic :: System :: Systems Administration
Classifier: Topic :: Terminals
Classifier: Topic :: Utilities
Requires-Python: >=3.11
Requires-Dist: pfzy>=0.3.4
Requires-Dist: pydantic-settings[yaml]>=2.7.0
Requires-Dist: pydantic>=2.10.4
Requires-Dist: textual>=3.0.0
Requires-Dist: types-pyyaml>=6.0.12.20241221
Requires-Dist: xdg-base-dirs>=6.0.0
